xlsxutility/__init__.py
xlsxutility/align.py
xlsxutility/autofit.py
xlsxutility-1.1.dist-info/LICENSE
xlsxutility-1.1.dist-info/METADATA
xlsxutility-1.1.dist-info/WHEEL
xlsxutility-1.1.dist-info/top_level.txt
xlsxutility-1.1.dist-info/RECORD
