Metadata-Version: 2.1
Name: xlsxutility
Version: 1.1
Summary: Helper functions for .xlsx files
Home-page: https://github.com/MattDJensen/Xlsx_Utility_Package
Author: Matthew Jensen
Author-email: matt@matthewjensen.dev
License: MIT
Download-URL: https://github.com/MattDJensen/Xlsx_Utility_Package/archive/1.1.tar.gz
Platform: UNKNOWN
Classifier: License :: OSI Approved :: MIT License
Classifier: Programming Language :: Python :: 3
Classifier: Programming Language :: Python :: 3.8
Classifier: Operating System :: OS Independent
Requires-Python: >=3.6
Requires-Dist: xlsxwriter
